weppy_BS3-0.6.dist-info/DESCRIPTION.rst
weppy_BS3-0.6.dist-info/METADATA
weppy_BS3-0.6.dist-info/RECORD
weppy_BS3-0.6.dist-info/WHEEL
weppy_BS3-0.6.dist-info/metadata.json
weppy_BS3-0.6.dist-info/top_level.txt
weppy_bs3/__init__.py
weppy_bs3/ext.py
weppy_bs3/assets/bootstrap-datetimepicker.min.css
weppy_bs3/assets/bootstrap-datetimepicker.min.js
weppy_bs3/assets/bootstrap.min.css
weppy_bs3/assets/bootstrap.min.js
weppy_bs3/assets/moment.min.js
