Metadata-Version: 2.0
Name: weppy-BS3
Version: 0.6
Summary: Bootstrap3 UI elements for weppy
Home-page: https://github.com/gi0baro/weppy-bs3
Author: Giovanni Barillari
Author-email: gi0baro@d4net.org
License: BSD
Platform: any
Classifier: Development Status :: 4 - Beta
Classifier: Environment :: Web Environment
Classifier: Intended Audience :: Developers
Classifier: License :: OSI Approved :: BSD License
Classifier: Operating System :: OS Independent
Classifier: Programming Language :: Python
Classifier: Programming Language :: Python :: 2
Classifier: Programming Language :: Python :: 3
Classifier: Topic :: Internet :: WWW/HTTP :: Dynamic Content
Classifier: Topic :: Software Development :: Libraries :: Python Modules
Requires-Dist: weppy (>=1.2)
